requests_cache/__init__.py
requests_cache/compat.py
requests_cache/core.py
requests_cache/backends/__init__.py
requests_cache/backends/base.py
requests_cache/backends/mongo.py
requests_cache/backends/redis.py
requests_cache/backends/sqlite.py
requests_cache/backends/storage/__init__.py
requests_cache/backends/storage/dbdict.py
requests_cache/backends/storage/mongodict.py
requests_cache/backends/storage/redisdict.py
requests_cache_latest-0.4.12.dist-info/DESCRIPTION.rst
requests_cache_latest-0.4.12.dist-info/METADATA
requests_cache_latest-0.4.12.dist-info/RECORD
requests_cache_latest-0.4.12.dist-info/WHEEL
requests_cache_latest-0.4.12.dist-info/metadata.json
requests_cache_latest-0.4.12.dist-info/top_level.txt
