Metadata-Version: 2.0
Name: requests-cache-latest
Version: 0.4.12
Summary: Persistent cache for requests library
Home-page: https://github.com/reclosedev/requests-cache
Author: Roman Haritonov
Author-email: reclosedev@gmail.com
License: BSD License
Keywords: requests,cache,persistence
Platform: UNKNOWN
Classifier: License :: OSI Approved :: BSD License
Classifier: Development Status :: 4 - Beta
Classifier: Intended Audience :: Developers
Classifier: Topic :: Software Development :: Libraries :: Python Modules
Classifier: Programming Language :: Python
Classifier: Programming Language :: Python :: 2.6
Classifier: Programming Language :: Python :: 2.7
Classifier: Programming Language :: Python :: 3
Requires-Dist: requests (>=1.1.0)
